drf_base64_binaryfield/__init__.py
drf_base64_binaryfield/fields.py
drf_base64_binaryfield/locale/nl_NL/LC_MESSAGES/django.mo
drf_base64_binaryfield/locale/nl_NL/LC_MESSAGES/django.po
drf_base64_binaryfield/validators.py
drf_base64_binaryfield-1.0.0.dist-info/LICENSE
drf_base64_binaryfield-1.0.0.dist-info/METADATA
drf_base64_binaryfield-1.0.0.dist-info/WHEEL
drf_base64_binaryfield-1.0.0.dist-info/RECORD
