Metadata-Version: 2.1
Name: drf-base64-binaryfield
Version: 1.0.0
Summary: Support for base64-encoded binary data in django rest framework serializers
Home-page: https://github.com/Stormbase/drf-base64-binaryfield
License: MIT
Author: Storm Heg
Author-email: storm@stormbase.digital
Requires-Python: >=3.9,<4.0
Classifier: Development Status :: 5 - Production/Stable
Classifier: Environment :: Web Environment
Classifier: Framework :: Django
Classifier: Framework :: Django :: 3.2
Classifier: Framework :: Django :: 4.0
Classifier: Framework :: Django :: 4.1
Classifier: Framework :: Django :: 4.2
Classifier: License :: OSI Approved :: MIT License
Classifier: Programming Language :: Python :: 3
Classifier: Programming Language :: Python :: 3.9
Classifier: Programming Language :: Python :: 3.10
Classifier: Programming Language :: Python :: 3.11
Classifier: Programming Language :: Python :: 3.12
Requires-Dist: django (>=3.2)
Requires-Dist: djangorestframework (>=3.14)
Project-URL: Changelog, https://github.com/Stormbase/drf-base64-binaryfield/releases
Project-URL: Documentation, https://drf-base64-binaryfield.readthedocs.io
Project-URL: Repository, https://github.com/Stormbase/drf-base64-binaryfield
